ptsnet/__init__.py
ptsnet/arrays/__init__.py
ptsnet/arrays/arrays.py
ptsnet/arrays/selectors.py
ptsnet/epanet/__init__.py
ptsnet/epanet/io.py
ptsnet/epanet/toolkit.py
ptsnet/epanet/util.py
ptsnet/examples/B0.inp
ptsnet/examples/B0_0.inp
ptsnet/examples/B0_1.inp
ptsnet/examples/B0_SURGE.inp
ptsnet/examples/B1_0.inp
ptsnet/examples/B1_1.inp
ptsnet/examples/B2.inp
ptsnet/examples/B3.inp
ptsnet/examples/B4.inp
ptsnet/examples/BWSN_F.inp
ptsnet/examples/LOOP.inp
ptsnet/examples/PIPE_IN_SERIES.inp
ptsnet/examples/Readme.md
ptsnet/examples/TNET3.inp
ptsnet/graphics/__init__.py
ptsnet/graphics/static.py
ptsnet/parallel/__init__.py
ptsnet/parallel/comm.py
ptsnet/parallel/partitioning.py
ptsnet/parallel/worker.py
ptsnet/profiler/__init__.py
ptsnet/profiler/profiler.py
ptsnet/results/__init__.py
ptsnet/results/file_structure.json
ptsnet/results/metadata.json
ptsnet/results/plots.py
ptsnet/results/storage.py
ptsnet/results/workspaces.py
ptsnet/simulation/__init__.py
ptsnet/simulation/_sfuncs.py
ptsnet/simulation/constants.py
ptsnet/simulation/funcs.py
ptsnet/simulation/init.py
ptsnet/simulation/sim.py
ptsnet/simulation/validation.py
ptsnet/utils/__init__.py
ptsnet/utils/analytics.py
ptsnet/utils/data.py
ptsnet/utils/io.py
ptsnet/utils/tacc.py
ptsnet-0.1.10.dist-info/licenses/LICENSE.txt
ptsnet-0.1.10.dist-info/METADATA
ptsnet-0.1.10.dist-info/WHEEL
ptsnet-0.1.10.dist-info/top_level.txt
ptsnet-0.1.10.dist-info/RECORD
