Metadata-Version: 2.4
Name: ptsnet
Version: 0.1.10
Summary: Parallel Transient Simulation in Water Networks
Home-page: https://github.com/gandresr/PTSNET
Author: Gerardo Riano
Author-email: griano@utexas.edu
Project-URL: Bug Tracker, https://github.com/gandresr/PTSNET/issues
Classifier: Programming Language :: Python :: 3
Classifier: License :: OSI Approved :: The Unlicense (Unlicense)
Classifier: Operating System :: OS Independent
Requires-Python: >=3.6
License-File: LICENSE.txt
Dynamic: author
Dynamic: author-email
Dynamic: classifier
Dynamic: description
Dynamic: description-content-type
Dynamic: home-page
Dynamic: license-file
Dynamic: project-url
Dynamic: requires-python
Dynamic: summary
